pixalate_open_mcp/__init__.py
pixalate_open_mcp/__version__.py
pixalate_open_mcp/models/__init__.py
pixalate_open_mcp/models/analytics.py
pixalate_open_mcp/models/config.py
pixalate_open_mcp/models/dimensions.py
pixalate_open_mcp/models/enrichment.py
pixalate_open_mcp/models/fraud.py
pixalate_open_mcp/models/metadata.py
pixalate_open_mcp/models/tools.py
pixalate_open_mcp/server/__init__.py
pixalate_open_mcp/server/app.py
pixalate_open_mcp/tools/__init__.py
pixalate_open_mcp/tools/analytics/__init__.py
pixalate_open_mcp/tools/analytics/tools.py
pixalate_open_mcp/tools/enrichment/__init__.py
pixalate_open_mcp/tools/enrichment/tools.py
pixalate_open_mcp/tools/fraud/__init__.py
pixalate_open_mcp/tools/fraud/tools.py
pixalate_open_mcp/utils/__init__.py
pixalate_open_mcp/utils/exponential_backoff.py
pixalate_open_mcp/utils/logging_config.py
pixalate_open_mcp/utils/request.py
pixalate_open_mcp-1.0.1.dist-info/METADATA
pixalate_open_mcp-1.0.1.dist-info/WHEEL
pixalate_open_mcp-1.0.1.dist-info/entry_points.txt
pixalate_open_mcp-1.0.1.dist-info/licenses/LICENSE
pixalate_open_mcp-1.0.1.dist-info/RECORD
