Metadata-Version: 2.4
Name: pixalate-open-mcp
Version: 1.0.1
Summary: Pixalate Open MCP Server
Project-URL: Homepage, https://pixalate.github.io/pixalate-open-mcp/
Project-URL: Repository, https://github.com/pixalate-inc/pixalate-open-mcp
Project-URL: Documentation, https://pixalate.github.io/pixalate-open-mcp/
Author-email: Ezequiel <info@pixalate.com>
License-File: LICENSE
Keywords: python
Classifier: Intended Audience :: Developers
Classifier: Programming Language :: Python
Classifier: Programming Language :: Python :: 3
Classifier: Programming Language :: Python :: 3.12
Classifier: Programming Language :: Python :: 3.13
Classifier: Topic :: Software Development :: Libraries :: Python Modules
Requires-Python: <4.0,>=3.12
Requires-Dist: mcp>=1.0.0
Requires-Dist: mcp[cli]>=1.0.0
Requires-Dist: requests==2.32.4
